{
    "schema":  "BRANCH_AGNOSTIC_MAP_REFRESH_RESULT_V3",
    "status":  "MAP_REFRESHED",
    "checked_at":  "2026-07-07T10:04:31.9488972+04:00",
    "branch":  "main",
    "observed_head":  "d3deb1a034a0afdd6026a17add92f880b2b2eaae",
    "subject_head":  "d3deb1a034a0afdd6026a17add92f880b2b2eaae",
    "trigger_reason":  "git_pre_commit_composition_map_auto_refresh",
    "force":  true,
    "dry_run":  false,
    "changed_paths":  [
                          "operations/live_readiness/run_school_aimo_live_readiness_gate_v1.ps1",
                          "operations/live_readiness/validate_school_aimo_live_readiness_gate_v1.ps1",
                          "reports/self_development/SELF_MODEL_ACTIVE_MAP.json",
                          "reports/self_development/agent_body_map.json",
                          "reports/self_development/agent_body_map.md",
                          "reports/self_development/branch_agnostic_map_refresh_result.json"
                      ],
    "structural_paths":  [
                             "operations/live_readiness/run_school_aimo_live_readiness_gate_v1.ps1",
                             "operations/live_readiness/validate_school_aimo_live_readiness_gate_v1.ps1"
                         ],
    "output_root":  "reports/self_development",
    "canonical_composition_map":  "reports/self_development/SELF_MODEL_ACTIVE_MAP.json",
    "human_composition_summary":  "reports/self_development/agent_body_map.md",
    "derived_compatibility_view":  "reports/self_development/agent_body_map.json",
    "protected_state_mutated":  false,
    "runtime_outputs_staged":  false,
    "live_process_touched":  false,
    "deletion_performed":  false,
    "body_source_fingerprint":  {
                                    "algorithm":  "sha256(sorted structural path plus file sha256; excludes reports/runtime/proofs/gpt_handoff archives)",
                                    "structural_file_count":  565,
                                    "sha256":  "e1d5940dc607c739123b3cf5327ec43f9ecf659079cb35db4669321307b89f88"
                                },
    "map_contains_required_components":  true,
    "required_components":  [
                                "school",
                                "school_source_router",
                                "compact_memory_intake",
                                "autonomous_inner_motor",
                                "map_control",
                                "gpt_handoff"
                            ],
    "skip_reason":  null,
    "freshness_rule":  "Currentness is body_source_fingerprint, not self-referential commit HEAD.",
    "missing_required_components":  [

                                    ],
    "build_result":  {
                         "result":  "PASS",
                         "builder":  "AGENT_BODY_COMPOSITION_MAP_V1",
                         "canonical_composition_map":  "reports/self_development/SELF_MODEL_ACTIVE_MAP.json",
                         "component_count":  7,
                         "structural_path_count":  565
                     },
    "refreshed_at":  "2026-07-07T10:04:32.8642581+04:00"
}
