{
    "schema":  "mind_logic_deep_audit_plan_v1_acceptance",
    "status":  "ACCEPTED_STRATEGY_SUPPORTED_MIND_LOGIC_DEEP_AUDIT_PLAN_V1",
    "checked_at":  "2026-07-17T19:09:28.8005501Z",
    "plan":  "AGENT_BUILDER_MIND_LOGIC_DEEP_AUDIT_PLAN_V1.md",
    "transition_plan_status":  "PHASE_PROVEN_LAB_NOT_CANONICAL_REPLACEMENT",
    "current_life_reality":  {
                                 "canonical_launcher":  "operations/autonomous_inner_motor/start_agent_life_v1.ps1",
                                 "canonical_runner":  "operations/autonomous_inner_motor/run_autonomous_inner_motor.ps1",
                                 "ram_lab":  "operations/autonomous_inner_motor/run_continuous_agent_runtime_v1_lab.ps1",
                                 "ram_lab_status":  "PROVEN_LAB_NOT_CANONICAL"
                             },
    "first_audit":  "AUDIT_M1_CURRENT_MIND_TOPOLOGY_V1",
    "candidate_organs":  [
                             "SELECTIVE_COMPACT_MEMORY_RETRIEVAL_V1",
                             "FRONTIER_TO_BUILD_TASK_ROUTER_V1",
                             "LOOP_STALL_DETECTOR_V1",
                             "DECISION_UTILITY_SCORE_V1",
                             "PARENT_GOAL_RETURN_GATE_V1"
                         ],
    "boundary":  {
                     "plan_only":  true,
                     "runtime_launched":  false,
                     "active_memory_mutated":  false,
                     "canonical_launcher_mutated":  false,
                     "cycle_runner_mutated":  false,
                     "transition_plan_deleted":  false
                 }
}
